agent_workshop/__init__.py
agent_workshop/agent.py
agent_workshop/config.py
agent_workshop/py.typed
agent_workshop/agents/__init__.py
agent_workshop/agents/data_science/__init__.py
agent_workshop/agents/data_science/notebook_validator_generated.py
agent_workshop/agents/pipelines/__init__.py
agent_workshop/agents/pipelines/validation.py
agent_workshop/agents/software_dev/__init__.py
agent_workshop/agents/software_dev/code_reviewer.py
agent_workshop/agents/software_dev/pr_comment_processor.py
agent_workshop/agents/software_dev/pr_pipeline.py
agent_workshop/agents/software_dev/presets.py
agent_workshop/agents/software_dev/release_pipeline.py
agent_workshop/agents/validators/__init__.py
agent_workshop/agents/validators/deliverable.py
agent_workshop/agents/validators/presets.py
agent_workshop/blueprints/__init__.py
agent_workshop/blueprints/agent_builder.py
agent_workshop/blueprints/code_generator.py
agent_workshop/blueprints/schema.py
agent_workshop/blueprints/validators.py
agent_workshop/providers/__init__.py
agent_workshop/providers/anthropic_api.py
agent_workshop/providers/base.py
agent_workshop/providers/claude_agent_sdk.py
agent_workshop/utils/__init__.py
agent_workshop/utils/langfuse_helpers.py
agent_workshop/workflows/__init__.py
agent_workshop/workflows/langgraph_agent.py
agent_workshop-0.3.0.dist-info/METADATA
agent_workshop-0.3.0.dist-info/WHEEL
agent_workshop-0.3.0.dist-info/licenses/LICENSE
agent_workshop-0.3.0.dist-info/RECORD
