Metadata-Version: 2.4
Name: agent-workshop
Version: 0.3.0
Summary: Batteries-included framework for building automation-focused AI agents with observability
Project-URL: Homepage, https://github.com/trentleslie/agent-workshop
Project-URL: Documentation, https://github.com/trentleslie/agent-workshop#readme
Project-URL: Repository, https://github.com/trentleslie/agent-workshop
Project-URL: Issues, https://github.com/trentleslie/agent-workshop/issues
Author-email: trentleslie <trentleslie@gmail.com>
License: MIT
License-File: LICENSE
Keywords: agents,ai,anthropic,automation,claude,langfuse,langgraph,observability
Classifier: Development Status :: 3 - Alpha
Classifier: Intended Audience :: Developers
Classifier: License :: OSI Approved :: MIT License
Classifier: Programming Language :: Python :: 3
Classifier: Programming Language :: Python :: 3.10
Classifier: Programming Language :: Python :: 3.11
Classifier: Programming Language :: Python :: 3.12
Classifier: Topic :: Scientific/Engineering :: Artificial Intelligence
Classifier: Topic :: Software Development :: Libraries :: Python Modules
Requires-Python: >=3.10
Requires-Dist: anthropic>=0.40.0
Requires-Dist: claude-code-sdk>=0.0.25
Requires-Dist: jinja2>=3.1.6
Requires-Dist: langfuse>=3.0.0
Requires-Dist: langgraph>=0.2.0
Requires-Dist: pydantic-settings>=2.0.0
Requires-Dist: pydantic>=2.0.0
Requires-Dist: python-dotenv>=1.0.0
Requires-Dist: tiktoken>=0.7.0
Provides-Extra: agents
Requires-Dist: claude-agent-sdk>=0.1.0; extra == 'agents'
Requires-Dist: langgraph>=0.2.0; extra == 'agents'
Requires-Dist: pyyaml>=6.0; extra == 'agents'
Provides-Extra: claude-agent
Requires-Dist: claude-agent-sdk>=0.1.0; extra == 'claude-agent'
Provides-Extra: dev
Requires-Dist: mypy>=1.11.0; extra == 'dev'
Requires-Dist: pytest-asyncio>=0.23.0; extra == 'dev'
Requires-Dist: pytest>=8.0.0; extra == 'dev'
Requires-Dist: ruff>=0.6.0; extra == 'dev'
Provides-Extra: pipelines
Requires-Dist: claude-agent-sdk>=0.1.0; extra == 'pipelines'
Requires-Dist: langgraph>=0.2.0; extra == 'pipelines'
Requires-Dist: pyyaml>=6.0; extra == 'pipelines'
Provides-Extra: validators
Requires-Dist: claude-agent-sdk>=0.1.0; extra == 'validators'
Requires-Dist: pyyaml>=6.0; extra == 'validators'
